Workbook

Sheet Summary
A1: Vox Ops — Big picture
A2: Auto-calcs from Clients + Costs + Leads. Yellow = edit. Green = from other sheets.
A4: REVENUE
A5: Active clients | B5: =Clients!B38
A6: Monthly recurring revenue (MRR) | B6: =Clients!B39
A7: Annual run rate (MRR x 12) | B7: =B6*12
A9: COSTS
A10: Active tool/overhead costs | B10: =Costs!B29
A11: Client cost-to-serve (sum) | B11: =Clients!B40
A12: Total monthly costs | B12: =B10+B11
A14: MARGIN
A15: Gross margin ($) | B15: =B6-B12
A16: Gross margin % | B16: =IF(B6=0,"-",B15/B6)
A18: PIPELINE (from Leads)
A19: New | B19: =Leads!B57
A20: Audit booked | B20: =Leads!B58
A21: Audit done | B21: =Leads!B59
A22: Setup | B22: =Leads!B60
A23: Lost | B23: =Leads!B62
A25: REPLACE 9-5 CHECK
A26: Target personal income $/mo (edit) | B26: 10000
A27: MRR vs target | B27: =B6-B26
A28: Bundle seats needed @ default quote | B28: =IF(SKUs!E8=0,"-",ROUNDUP(B26/SKUs!E8,0))
A29: (Uses Bundle Default Quote on SKUs — row 8)
A31: Weekly habits
A32: • Log every lead same day (BNI, form, call)
A33: • After each audit: Status + Quoted + Est. leak
A34: • When they pay: Clients row + Lead Status = Live
A35: • Monthly: update Costs, send reports, tick Report sent?
A36: • No client dashboard — this sheet is your ops brain
A38: Google Sheets: drive.google.com → New → File upload → Vox-Ops.xlsx OR blank Sheet → File → Import → Upload

Sheet SKUs
A1: Vox Ops — Productized SKUs
A2: Blue text / yellow cells = edit these. Prices drive quotes.
A4: SKU | B4: Tagline | C4: Price Low ($/mo) | D4: Price High ($/mo) | E4: Default Quote ($/mo) | F4: Best For | G4: Notes
A5: Reviews | B5: AI Review Agent | C5: 300 | D5: 500 | E5: 400 | F5: Fastest visible win; map pack | G5: Start if budget-sensitive
A6: Receptionist | B6: AI Receptionist | C6: 500 | D6: 800 | E6: 650 | F6: Conversation capture | G6: Qualify + book + notify
A7: Voice | B7: AI Phone Agent | C7: 800 | D7: 1500 | E7: 1000 | F7: Missed / after-hours calls | G7: Highest revenue impact
A8: Bundle | B8: All three — AI front desk | C8: 1500 | D8: 1500 | E8: 1500 | F8: Default close | G8: Less than part-time hire
A10: Geography (ICP triangle)
A11: Primary cities | B11: Turlock, Modesto, Manteca
A12: Trades | B12: HVAC, Plumbing, Electrical
A13: Your base | B13: Turlock, CA
A15: How to use
A16: Edit yellow Default Quote when pricing changes. Bundle is the default pitch.

Sheet Leads
A1: Vox Ops — Leads (pipeline)
A2: Every inquiry: BNI, website form, referral, cold. Update Status as they move.
A4: Date | B4: Source | C4: Name | D4: Business | E4: Trade | F4: City | G4: Phone | H4: Email | I4: Status | J4: Interest | K4: Quoted $/mo | L4: Est. monthly leak $ | M4: Next step | N4: Next date | O4: Notes
A5: 2026-07-19 | B5: Website | E5: HVAC | F5: Turlock | I5: New | J5: Bundle | K5: 1500 | M5: Book audit | O5: Example row — replace or delete
A56: Pipeline counts
A57: New | B57: =COUNTIF(I5:I54,"New")
A58: Audit booked | B58: =COUNTIF(I5:I54,"Audit booked")
A59: Audit done | B59: =COUNTIF(I5:I54,"Audit done")
A60: Setup | B60: =COUNTIF(I5:I54,"Setup")
A61: Live (from leads tab) | B61: =COUNTIF(I5:I54,"Live")
A62: Lost | B62: =COUNTIF(I5:I54,"Lost")
A63: Total named leads | B63: =COUNTA(C5:C54)

Sheet Clients
A1: Vox Ops — Clients (paying)
A2: Add a row when they pay / go live. MRR drives Summary.
A4: Go-live date | B4: Business | C4: Contact | D4: Trade | E4: City | F4: SKU | G4: MRR ($) | H4: Cost to serve $/mo | I4: Gross margin $ | J4: Reviews start | K4: Reviews now | L4: Health | M4: Report sent? | N4: Notes
I5: =IF(G5="","",G5-H5)
I6: =IF(G6="","",G6-H6)
I7: =IF(G7="","",G7-H7)
I8: =IF(G8="","",G8-H8)
I9: =IF(G9="","",G9-H9)
I10: =IF(G10="","",G10-H10)
I11: =IF(G11="","",G11-H11)
I12: =IF(G12="","",G12-H12)
I13: =IF(G13="","",G13-H13)
I14: =IF(G14="","",G14-H14)
I15: =IF(G15="","",G15-H15)
I16: =IF(G16="","",G16-H16)
... I34: =IF(G34="","",G34-H34)
A37: Totals
A38: Active clients | B38: =COUNTA(B5:B34)
A39: Total MRR | B39: =SUM(G5:G34)
A40: Total cost to serve | B40: =SUM(H5:H34)
A41: Total gross margin | B41: =SUM(I5:I34)

Sheet Costs
A1: Vox Ops — Costs (your tools & overhead)
A2: What YOU pay. Leave $0 until you spend. Annual → monthly average.
A4: Item | B4: $/mo | C4: Category | D4: Active? | E4: Notes
A5: Domain / DNS | B5: 0 | C5: Infra | D5: Y | E5: Yearly / 12
A6: Vercel / hosting | B6: 0 | C6: Infra | D6: Y | E6: Hobby free until scale
A7: Formspree | B7: 0 | C7: Tools | D7: Y | E7: Free tier
A8: Google Workspace / email | B8: 0 | C8: Tools | D8: Y | E8: If you pay for email
A9: xAI / SpaceXAI API | B9: 0 | C9: AI | D9: N | E9: Only when live PoC is on
A10: Phone / telephony | B10: 0 | C10: AI | D10: N | E10: When Voice is production
A11: BNI dues (monthly avg) | B11: 0 | C11: Sales | D11: N | E11: Annual / 12 if you join
A12: Software other | B12: 0 | C12: Tools | D12: N
A13: Ads (Google/Meta) | B13: 0 | C13: Sales | D13: N | E13: Optional later
A14: Misc / buffer | B14: 0 | C14: Other | D14: N
A27: Cost totals
A28: All listed $/mo | B28: =SUM(B5:B24)
A29: Active only (Active? = Y) | B29: =SUMIF(D5:D24,"Y",B5:B24)
A30: Tip: $240/year domain → enter $20 in $/mo

Sheet README
A1: How to use Vox Ops ($0)
A3: 1. Upload to Google Drive → open with Google Sheets (or File → Import).
A4: 2. Edit yellow cells only. Green numbers are formulas from other tabs.
A5: 3. SKUs — set default prices once.
A6: 4. Leads — one row per inquiry; use dropdowns.
A7: 5. Clients — one row per paying business.
A8: 6. Costs — overhead; Active? = Y only for what you pay now.
A9: 7. Summary — MRR, costs, margin, pipeline, vs income target.
A10: 8. Website leads: paste from Formspree email into Leads.
A11: 9. Keep private — phones/emails.
A13: Product: Vox.chat · Base: Turlock, CA · Triangle: Turlock · Modesto · Manteca
A14: No client-facing dashboard. Internal ops only.
